error_explorer_flask/__init__.py
error_explorer_flask/extension.py
error_explorer_flask/logging.py
error_explorer_flask-1.2.0.dist-info/METADATA
error_explorer_flask-1.2.0.dist-info/WHEEL
error_explorer_flask-1.2.0.dist-info/RECORD
