Metadata-Version: 2.4
Name: error-explorer-flask
Version: 1.2.0
Summary: Error Explorer SDK for Flask
Project-URL: Documentation, https://docs.error-explorer.com/sdks/flask
Project-URL: Issues, https://github.com/error-explorer/error-explorer-flask/issues
Project-URL: Source, https://github.com/error-explorer/error-explorer-flask
Author-email: Error Explorer Team <support@error-explorer.com>
License-Expression: MIT
Keywords: error-explorer,error-tracking,flask,monitoring
Classifier: Development Status :: 5 - Production/Stable
Classifier: Framework :: Flask
Classifier: Intended Audience :: Developers
Classifier: License :: OSI Approved :: MIT License
Classifier: Programming Language :: Python :: 3
Classifier: Programming Language :: Python :: 3.9
Classifier: Programming Language :: Python :: 3.10
Classifier: Programming Language :: Python :: 3.11
Classifier: Programming Language :: Python :: 3.12
Classifier: Topic :: Software Development :: Libraries :: Python Modules
Requires-Python: >=3.9
Requires-Dist: error-explorer>=1.0.0
Requires-Dist: flask>=2.0.0
Provides-Extra: dev
Requires-Dist: pytest-cov>=4.0.0; extra == 'dev'
Requires-Dist: pytest>=7.0.0; extra == 'dev'
